setup.cfg
setup.py
gubser/__init__.py
gubser/gubser.py
gubser/gubser_cffi.py
gubser/riemann.py
gubser/riemann_cffi.py
gubser.egg-info/PKG-INFO
gubser.egg-info/SOURCES.txt
gubser.egg-info/dependency_links.txt
gubser.egg-info/requires.txt
gubser.egg-info/top_level.txt