Metadata-Version: 1.1
Name: gubser
Version: 0.9
Summary: Gubser solution for ideal hydrodynamics, 2+1D viscous hydrodynamics 
Home-page: https://github.com/snowhitiger/gubser
Author: Long-Gang Pang
Author-email: lgpang@qq.com
License: MIT
Download-URL: https://github.com/snowhitiger/gubser/tarball/0.9
Keywords: gubser,2nd order viscous hydrodynamics,python,clvisc
Platform: UNKNOWN
